{
  "objectInfo" : {
    "id" : "3vdX3noUewahmxj5SYSz0e",
    "name" : "BulkUnlink_LTF_FF_FF",
    "type" : "WORKFLOW",
    "metadata" : {
      "modelVersion" : {
        "major" : 0,
        "minor" : 0
      },
      "repoInfo" : {
        "repoHandle" : "0100030N0000000000EU"
      },
      "contextAttributes" : [ {
        "name" : "id",
        "value" : "@1"
      } ],
      "additionalInfo" : {
        "description" : null,
        "contentType" : "JSON",
        "documentState" : "VALID"
      }
    }
  },
  "dataFileExtension" : "zip",
  "objectRefs" : [ {
    "id" : "l3lVJrfMj4BiI1WAVFclMf",
    "name" : "BulkUnlink_LTF_Mapping_Task",
    "type" : "MTT",
    "metadata" : {
      "modelVersion" : {
        "major" : 0,
        "minor" : 0
      },
      "repoInfo" : {
        "repoHandle" : "0100030Z0000000001Q3"
      },
      "contextAttributes" : null,
      "additionalInfo" : {
        "description" : "",
        "contentType" : "JSON",
        "documentState" : "VALID"
      }
    },
    "path" : "/Explore/VCS_PROJ_UI/BulkUnlink_FOLDER"
  }, {
    "id" : "kKeP5yj0j8hkwmve9hBKil",
    "name" : "BulkUnlink_LTF_DSS_FF_FF",
    "type" : "DSS",
    "metadata" : {
      "modelVersion" : {
        "major" : 0,
        "minor" : 0
      },
      "repoInfo" : {
        "repoHandle" : "0100030I0000000001E9"
      },
      "contextAttributes" : null,
      "additionalInfo" : {
        "description" : "",
        "contentType" : "JSON",
        "documentState" : "VALID"
      }
    },
    "path" : "/Explore/VCS_PROJ_UI"
  } ]
}