{
  "objectInfo" : {
    "id" : "6H8X2N7KQeeh7QRROA6pas",
    "name" : "BulkUnlink_LTF_FF_FF",
    "type" : "WORKFLOW",
    "metadata" : {
      "modelVersion" : {
        "major" : 0,
        "minor" : 0
      },
      "repoInfo" : {
        "repoHandle" : "0100JT0N00000000006I"
      },
      "contextAttributes" : [ {
        "name" : "id",
        "value" : "@1"
      } ],
      "additionalInfo" : {
        "description" : null,
        "contentType" : "JSON",
        "documentState" : "VALID"
      }
    }
  },
  "dataFileExtension" : "zip",
  "objectRefs" : [ {
    "id" : "9vhkmhSRHMgitQCdBuCRQN",
    "name" : "BulkUnlink_LTF_DSS_FF_FF",
    "type" : "DSS",
    "metadata" : {
      "modelVersion" : {
        "major" : 0,
        "minor" : 0
      },
      "repoInfo" : {
        "repoHandle" : "0100JT0I00000000015Z"
      },
      "contextAttributes" : null,
      "additionalInfo" : {
        "description" : "",
        "contentType" : "JSON",
        "documentState" : "VALID"
      }
    },
    "path" : "/Explore/VCS_PROJ_UI"
  }, {
    "id" : "5blZ7C7Ijqgig9p3Levs02",
    "name" : "BulkUnlink_LTF_Mapping_Task",
    "type" : "MTT",
    "metadata" : {
      "modelVersion" : {
        "major" : 0,
        "minor" : 0
      },
      "repoInfo" : {
        "repoHandle" : "0100JT0Z0000000000V8"
      },
      "contextAttributes" : null,
      "additionalInfo" : {
        "description" : "",
        "contentType" : "JSON",
        "documentState" : "VALID"
      }
    },
    "path" : "/Explore/VCS_PROJ_UI/BulkUnlink_FOLDER"
  } ]
}