{
  "objectInfo" : {
    "id" : "7OCNC48KDlmg41cfhn91qI",
    "name" : "BulkUnlink_LTF_Mapping",
    "type" : "DTEMPLATE",
    "metadata" : {
      "modelVersion" : {
        "major" : 0,
        "minor" : 0
      },
      "repoInfo" : {
        "repoHandle" : "010UPX17000000000005"
      },
      "contextAttributes" : [ {
        "name" : "id",
        "value" : "@1"
      } ],
      "additionalInfo" : {
        "description" : "",
        "contentType" : "JSON",
        "documentState" : "VALID"
      }
    }
  },
  "dataFileExtension" : "zip",
  "objectRefs" : [ {
    "id" : "lLk4KjRQzA6cD460jvbZah",
    "name" : "FF_PodCertification",
    "type" : "Connection",
    "metadata" : {
      "modelVersion" : {
        "major" : 0,
        "minor" : 0
      },
      "repoInfo" : {
        "repoHandle" : "010UPX0B000000000003"
      },
      "contextAttributes" : null,
      "additionalInfo" : {
        "description" : "Flat File connection for Pod Certification Automation",
        "contentType" : "JSON",
        "documentState" : "COMPLETE"
      }
    },
    "path" : "/SYS"
  } ]
}