{
  "objectInfo" : {
    "id" : "21PSchYOkJhjsXPI2sdv0z",
    "name" : "BulkUnlink_LTF_FF_FF",
    "type" : "WORKFLOW",
    "metadata" : {
      "modelVersion" : {
        "major" : 0,
        "minor" : 0
      },
      "repoInfo" : {
        "repoHandle" : "01002U0N000000000074"
      },
      "contextAttributes" : [ {
        "name" : "id",
        "value" : "@1"
      } ],
      "additionalInfo" : {
        "description" : null,
        "contentType" : "JSON",
        "documentState" : "VALID"
      }
    }
  },
  "dataFileExtension" : "zip",
  "objectRefs" : [ {
    "id" : "4IZnxbzIBDxezf9ghjiD6V",
    "name" : "BulkUnlink_LTF_Mapping_Task",
    "type" : "MTT",
    "metadata" : {
      "modelVersion" : {
        "major" : 0,
        "minor" : 0
      },
      "repoInfo" : {
        "repoHandle" : "01002U0Z0000000000RX"
      },
      "contextAttributes" : null,
      "additionalInfo" : {
        "description" : "",
        "contentType" : "JSON",
        "documentState" : "VALID"
      }
    },
    "path" : "/Explore/VCS_PROJ_UI/BulkUnlink_FOLDER"
  }, {
    "id" : "2444c0DcuQZlbycbSCLqyB",
    "name" : "BulkUnlink_LTF_DSS_FF_FF",
    "type" : "DSS",
    "metadata" : {
      "modelVersion" : {
        "major" : 0,
        "minor" : 0
      },
      "repoInfo" : {
        "repoHandle" : "01002U0I0000000000TK"
      },
      "contextAttributes" : null,
      "additionalInfo" : {
        "description" : "",
        "contentType" : "JSON",
        "documentState" : "VALID"
      }
    },
    "path" : "/Explore/VCS_PROJ_UI"
  } ]
}