{
  "objectInfo" : {
    "id" : "6rPHb0JvxtojX6hHSD82kl",
    "name" : "MultiProjPullDependency2_YTM0MmE4Y2YtNzc5My00Nj",
    "type" : "Project",
    "metadata" : {
      "modelVersion" : {
        "major" : 0,
        "minor" : 0
      },
      "repoInfo" : null,
      "contextAttributes" : [ ],
      "additionalInfo" : {
        "description" : "created with automation dependency2 project for multi pull",
        "contentType" : "Binary",
        "documentState" : "COMPLETE"
      }
    }
  },
  "dataFileExtension" : "json",
  "objectRefs" : [ ]
}