{
  "objectInfo" : {
    "id" : "6tmxV5o6N9tfoIXV2y13Ys",
    "name" : "MultiProjPullDependency1_MGY5ZjM2YmMtNDZlOC00Nz",
    "type" : "Project",
    "metadata" : {
      "modelVersion" : {
        "major" : 0,
        "minor" : 0
      },
      "repoInfo" : null,
      "contextAttributes" : [ ],
      "additionalInfo" : {
        "description" : "created with automation dependency1 project for multi pull",
        "contentType" : "Binary",
        "documentState" : "COMPLETE"
      }
    }
  },
  "dataFileExtension" : "json",
  "objectRefs" : [ ]
}